{"category":"Doujinshi","dumped":1768127381,"expunged":false,"filecount":"50","filesize":155259938,"gid":3732696,"posted":"1768123833","rating":"4.79","tags":["language:korean","language:translated","group:tokonatsu sanshouuo","artist:pegina","male:dilf","female:school swimsuit","female:sole female"],"thumb":"https://ehgt.org/w/02/197/06202-7yf2ck4g.webp","title":"[Tokonatsu Sanshouuo (Pegina)] Otokogirai JC Oji-san to Isshuukan Koibito Keiyaku | 남자가 싫은 JC 아저씨와 일주일간 연인 계약 [Korean] [Digital]","title_jpn":"[常夏山椒魚 (ぺぎな)] 男嫌いJCおじさんと一週間恋人契約 [韓国翻訳] [DL版]","token":"ababc7f286","torrentcount":"1","torrents":[{"added":"1768123892","fsize":"154669174","hash":"4b918c471d365f2d677ff82f4b44f09d685588a9","name":"[Tokonatsu Sanshouuo (Pegina)] Otokogirai JC Oji-san to Isshuukan Koibito Keiyaku [Korean][Digital].zip","tsize":"6310"}],"uploader":"ongirl"}