{"category": "Misc", "expunged": false, "filecount": "1837", "filesize": 629536227, "gid": 3732240, "posted": "1768100640", "rating": "3.63", "tags": ["parody:bleach", "parody:dungeon ni deai o motomeru no wa machigatteiru darou ka", "parody:oshi no ko", "character:ai hoshino", "character:hestia", "character:kana arima", "character:yoruichi shihoin", "male:goblin", "other:ai generated"], "thumb": "https://ehgt.org/w/02/189/57743-rywodpf1.webp", "title": "[patreon]-PIPITUA(AI Generated)（2025.12) Part 1", "title_jpn": "", "token": "3d5584b7bf", "torrentcount": "1", "torrents": [{"added": "1768100968", "fsize": "629159934", "hash": "e058d94734bde169f47a71e361cf8c10c98d3580", "name": "[patreon]-PIPITUA(AI Generated)（2025.12) Part 1.zip", "tsize": "6360"}], "uploader": "AHFZS", "dumped": 1768104327}