{"category":"Misc","dumped":1768167833,"expunged":false,"filecount":"14","filesize":16111691,"gid":3733625,"posted":"1768165503","rating":"1.13","tags":["language:speechless","male:goblin","female:blindfold","female:blowjob","female:bondage","female:double penetration","female:filming","female:gag","female:rape","mixed:group","mixed:mmf threesome","other:ai generated"],"thumb":"https://ehgt.org/w/02/197/70312-r46ldn8u.webp","title":"[PipiDoge] 哥布林入侵 [AI Generated]","title_jpn":"","token":"047a4bce62","torrentcount":"1","torrents":[{"added":"1768165552","fsize":"16116423","hash":"45d47142a30e9263fab58673720dea4408e1938d","name":"[PipiDoge] 哥布林入侵 [AI Generated].zip","tsize":"10169"}],"uploader":"yyyun"}