{"category":"Doujinshi","dumped":1768185097,"expunged":false,"filecount":"17","filesize":40796305,"first_gid":"3733045","first_key":"1cc000f118","gid":3733961,"parent_gid":"3733045","parent_key":"1cc000f118","posted":"1768180708","rating":"4.57","tags":["language:english","language:translated","parody:original","group:shinsei lolishota","artist:kozi","artist:shuffle","male:anal","male:anal intercourse","male:bbm","male:blowjob","male:blowjob face","male:crossdressing","male:dilf","male:elf","male:exhibitionism","male:exposed clothing","male:garter belt","male:hidden sex","male:high heels","male:lingerie","male:males only","male:mesuiki","male:phimosis","male:stockings","male:thigh high boots","male:tomgirl","male:yaoi","other:full color","other:multi-work series","other:uncensored"],"thumb":"https://ehgt.org/w/02/197/29547-mop5vlqk.webp","title":"Shinsei Lolishota (Shinsei Frontier) (shuffle, kozi)] Another World&#039;s Trap&#039;s Sinful Tryst ~Corrupted Holy Knight&#039;s Outdoor Bitch-walk~ [English] [Decensored] [Digital]","title_jpn":"[新生ロリショタ (新生フロンティア) (shuffle、kozi)] 異世界オトコノコ背徳密会 〜堕ちた少年聖騎士の野外メス犬散歩〜 [英訳] [無修正] [DL版]","token":"feef43644c","torrentcount":"1","torrents":[{"added":"1768180761","fsize":"40462474","hash":"0377bc8e71f2aeeea48ad3535022356bf7f0684b","name":"Shinsei Lolishota (Shinsei Frontier) (shuffle, kozi)] Another World&#039;s Trap&#039;s Sinful Tryst ~Corrupted Holy Knight&#039;s Outdoor Bitch-walk~ [English] [Decensored] [Digital].zip","tsize":"6637"}],"uploader":"AZeya"}