{"category":"Misc","dumped":1768218899,"expunged":false,"filecount":"159","filesize":161675260,"gid":3734488,"posted":"1768216314","rating":"1.50","tags":["other:ai generated"],"thumb":"https://ehgt.org/w/02/198/48041-7xff242m.webp","title":"[Martinez] Fan request:Cynthia [AI Generated]","title_jpn":"","token":"3d17ca69eb","torrentcount":"1","torrents":[{"added":"1768216400","fsize":"159266976","hash":"429b99443975c654fb90c3decdde8915b999fd44","name":"[Martinez] Fan requestCynthia [AI Generated].zip","tsize":"6414"}],"uploader":"KuruFapJikan"}