{"category":"Misc","dumped":1768190739,"expunged":false,"filecount":"49","filesize":196132636,"gid":3734029,"posted":"1768183939","rating":"2.64","tags":["parody:honkai star rail","character:ruan mei","other:ai generated","other:uncensored"],"thumb":"https://ehgt.org/w/02/195/98007-bukmad0n.webp","title":"[Reiji] Ruan Mei’s Office Elegance [AI Generated]","title_jpn":"","token":"081d4e70cc","torrentcount":"1","torrents":[{"added":"1768184008","fsize":"196164174","hash":"3dbcf984f982222b043d0ee54918eb5705c222b1","name":"[Reiji] Ruan Mei’s Office Elegance [AI Generated].zip","tsize":"7841"}],"uploader":"MoQiSzzKing"}