{"category":"Doujinshi","dumped":1768207544,"expunged":false,"filecount":"13","filesize":1407722,"gid":3734291,"posted":"1768202875","rating":"2.00","tags":["language:english","female:navel fuck","female:ryona"],"thumb":"https://ehgt.org/w/02/198/16945-acg6vmss.webp","title":"(R-18G)[ーYuna かみしろ(Pixiv)] High School Dance Competition Winners (English)","title_jpn":"(R-18G)[ーYuna かみしろ(Pixiv)] 高校ダンスコンテストの優勝者","token":"798385d50f","torrentcount":"1","torrents":[{"added":"1768202912","fsize":"1410055","hash":"eebbb0fc31f66d3bbb7bfbb3c4e71f1153f14d2d","name":"(R-18G)[ーYuna かみしろ(Pixiv)] High School Dance Competition Winners (English).zip","tsize":"2111"}],"uploader":"DakotaofRaptors"}