{"category":"Artist CG","dumped":1768279676,"expunged":false,"filecount":"11","filesize":14517200,"gid":3735580,"posted":"1768275133","rating":"2.00","tags":["parody:gotoubun no hanayome","character:ichika nakano","character:itsuki nakano","character:miku nakano","character:nino nakano","character:yotsuba nakano","artist:high cheese","female:big breasts","other:animated","other:variant set"],"thumb":"https://ehgt.org/w/02/199/50814-ernbc4eu.webp","title":"[FANBOX] [ミルクトラック] 五つ子たちが騎乗位でおっぱいを揺らし続けるGIFアニメ","title_jpn":"[FANBOX 限定公開] 五つ子たちが騎乗位でおっぱいを揺らし続けるGIFアニメ (Pixiv Fanbox)","token":"e707b0b5ec","torrentcount":"0","torrents":[],"uploader":"SPL263"}