{"category":"Doujinshi","dumped":1768254880,"expunged":false,"filecount":"8","filesize":12888066,"gid":3735177,"posted":"1768252210","rating":"1.63","tags":["parody:genshin impact","character:raiden shogun","artist:se34tai","male:sole male","female:sole female","other:full color"],"thumb":"https://ehgt.org/w/01/856/26445-skjefo60.webp","title":"[se34tai] 機能が止まっちゃう雷電将軍 (原神)","title_jpn":"[se34tai] 機能が止まっちゃう雷電将軍 (原神)","token":"7daae1d688","torrentcount":"0","torrents":[],"uploader":"ninetydollardoujin"}