{"category":"Western","dumped":1768276119,"expunged":false,"filecount":"28","filesize":32814447,"first_gid":"3631845","first_key":"e1200a5190","gid":3735527,"parent_gid":"3699208","parent_key":"2d508f3696","posted":"1768271686","rating":"2.17","tags":["language:spanish","language:translated","character:amber","character:elliot","character:flint","character:rita","artist:fuf","male:big penis","male:bisexual","male:dog","male:fox","male:furry","male:nakadashi","male:yaoi","female:bisexual","female:cunnilingus","female:fox","female:furry","female:nakadashi","female:stomach deformation","female:yuri","mixed:animal on animal","mixed:ffm threesome","mixed:group","mixed:mmf threesome","other:comic","other:full color","other:multi-work series","other:story arc"],"thumb":"https://ehgt.org/w/02/105/21970-6067x32k.webp","title":"[Fuf] Un Ardiente Camino 5 (Criaturas) [Spanish] [Ongoing]","title_jpn":"[Fuf] Blazing a Trail 5 (Critters) [Ongoing]","token":"7ebd6b9d6a","torrentcount":"0","torrents":[],"uploader":"Eevee 14"}