{"category":"Doujinshi","dumped":1768319114,"expunged":false,"filecount":"21","filesize":114149064,"gid":3736365,"posted":"1768315512","rating":"2.53","tags":["language:chinese","language:translated","parody:mushoku tensei","character:roxy migurdia","character:rudeus greyrat","artist:nak","male:sole male","female:lolicon","female:sole female","female:very long hair","other:multi-work series"],"thumb":"https://ehgt.org/w/02/200/36260-aq2ansno.webp","title":"(C106)[NAK(NAK) Can I have a little overnight tonight? As an exclusive private hall. Vol.2 ( If you go to another world","title_jpn":"(C106)[NAK(NAK)今宵はちょっとエッチなことしてもいいですか？専用オナホールとして… Vol.2 (無職転生 ～異世界行ったら本気だす～)天使半机翻汉化","token":"453b2d21e4","torrentcount":"0","torrents":[],"uploader":"uaciuahc"}