{"category":"Misc","dumped":1768300729,"expunged":false,"filecount":"78","filesize":151549307,"gid":3736062,"posted":"1768298433","rating":"2.56","tags":["parody:tate no yuusha no nariagari","other:ai generated"],"thumb":"https://ehgt.org/w/02/199/90171-i230p8em.webp","title":"[Digital Waifu Gallery] Mirelia Q Melromarc - The Rising of the Shield Hero (Patreon) [AI Generated]","title_jpn":"[Digital Waifu Gallery] ミレリア＝Ｑ＝メルロマルク - 盾の勇者の成り上がり (Patreon) [AI Generated]","token":"da83a6e4ea","torrentcount":"0","torrents":[],"uploader":"JoyBoy7890"}