{"category":"Misc","dumped":1768337928,"expunged":false,"filecount":"1052","filesize":1658801716,"first_gid":"3139728","first_key":"991445042b","gid":3736705,"parent_gid":"3725146","parent_key":"dd2ab53e88","posted":"1768335299","rating":"3.85","tags":["language:english","parody:koikatsu","male:blowjob","male:breast expansion","male:chastity belt","male:crossdressing","male:feminization","male:gender change","male:gender morph","male:spanking","male:yaoi","female:shemale","other:3d","other:multi-work series","other:story arc"],"thumb":"https://ehgt.org/w/01/661/85346-fxw4p3ld.webp","title":"[AndreaTG] Remember Me [?] (Chapter 1 - 9.3) (On-Going)","title_jpn":"","token":"bed5231cd8","torrentcount":"5","torrents":[{"added":"1762585162","fsize":"1386687226","hash":"96d6ceb458e1857ee7a08c5cd69c9697d54d9cf5","name":"AndreaTG - Remember Me 01-07.4 (795 pages, 20251107, ongoing).zip","tsize":"138251"},{"added":"1762585416","fsize":"449876049","hash":"26921b453059bda808c0413b9018702aeabcc4ab","name":"AndreaTG - Remember Me 01-07.4 (795 pages, 20251107, ongoing, JPG).zip","tsize":"90061"},{"added":"1764751127","fsize":"1450849710","hash":"22186c7d7939e2d543633e8fc59d7246c49ce867","name":"AndreaTG - Remember Me 01-8.2 (863pages 03Dec2025).zip","tsize":"55714"},{"added":"1766281163","fsize":"2050910925","hash":"9b4823c1568fc843007ea9920d3b9ca4ab09ff3c","name":"***OUTDATED*** Remember Me chap 01-09a - 1370 pages.zip","tsize":"203926"},{"added":"1767757352","fsize":"2103777839","hash":"de25cf30d6c2520ad67ee7aa2e2f31427aa8a376","name":"Remember Me chap 01-09b - 1425 pages.zip","tsize":"209178"}],"uploader":"AndreaTG"}