{"category":"Misc","dumped":1768395740,"expunged":false,"filecount":"456","filesize":805073604,"gid":3737479,"posted":"1768391366","rating":"5.00","tags":["parody:sword art online","character:asuna yuuki","character:sachi","female:netorare","other:ai generated","other:mosaic censorship"],"thumb":"https://ehgt.org/w/02/201/55756-cxb20ti8.webp","title":"[Isekai Bokujou (Ushi)] 快楽堕ち後のアスナとイチャらぶコスプレ性活 3+EX (Sword Art Online) [AI Generated]","title_jpn":"[異世界牧場（牛）] 快楽堕ち後のアスナとイチャらぶコスプレ性活 3+EX (ソードアート・オンライン) [AI生成]","token":"58e165ccc1","torrentcount":"1","torrents":[{"added":"1768392155","fsize":"804320505","hash":"11534ec87e07d42218b05d0ac8bb5adb8578350d","name":"[異世界牧場（牛）] 快楽堕ち後のアスナとイチャらぶコスプレ性活 3+EX (ソードアート・オンライン) [AI生成].zip","tsize":"62058"}],"uploader":"xusaku"}