{"category":"Misc","dumped":1768363337,"expunged":false,"filecount":"75","filesize":13735896,"gid":3737005,"posted":"1768360385","rating":"0.80","tags":["other:ai generated"],"thumb":"https://ehgt.org/w/02/200/46523-otqg5jl0.webp","title":"AetherMind AI - 狩野朱歌 Karino Shuka Extra [AI Generated]","title_jpn":"","token":"f48faab8d3","torrentcount":"1","torrents":[{"added":"1768360433","fsize":"13319943","hash":"4e71fe4ebc3de04b587d4d1275c232d5527f5ef3","name":"AetherMind AI - 狩野朱歌 Karino Shuka Extra [AI Generated].zip","tsize":"8490"}],"uploader":"AIDatabase"}