{"category":"Cosplay","dumped":1768489280,"expunged":false,"filecount":"10","filesize":31065061,"gid":3739265,"posted":"1768486414","rating":"1.17","tags":["parody:super mario brothers","character:rosalina","female:crown","female:eye-covering bang"],"thumb":"https://ehgt.org/w/02/189/79128-tfzkklng.webp","title":"Cplaya - Rosalina","title_jpn":"","token":"14635aa76d","torrentcount":"1","torrents":[{"added":"1768486473","fsize":"30981968","hash":"ede6ab45ac20eeec5c56c3239f5c3e72a972783f","name":"Cplaya - Rosalina.zip","tsize":"9765"}],"uploader":"b217285"}