{"category":"Misc","dumped":1768550152,"expunged":false,"filecount":"452","filesize":73341015,"first_gid":"3702978","first_key":"10947c357a","gid":3740341,"parent_gid":"3702978","parent_key":"10947c357a","posted":"1768547625","rating":"2.87","tags":["male:bald","other:ai generated"],"thumb":"https://ehgt.org/w/02/169/65111-4lu3vo04.webp","title":"秋田犬人 2 pixiv [AI Generated]","title_jpn":"","token":"7b37eb01b7","torrentcount":"1","torrents":[{"added":"1768547710","fsize":"72388593","hash":"e9e52c1a7dc104cd89222433b59a1b8e64bd7b92","name":"秋田犬人 2 pixiv [AI Generated].zip","tsize":"5864"}],"uploader":"jjjie"}