{"category":"Doujinshi","dumped":1768578127,"expunged":false,"filecount":"58","filesize":102250934,"first_gid":"3549724","first_key":"420be72b0d","gid":3740956,"parent_gid":"3549724","parent_key":"420be72b0d","posted":"1768575896","rating":"4.49","tags":["parody:blue archive","character:ayane okusora","character:sensei","character:shiroko sunaookami","group:jenoa cake","artist:takayaki","male:sole male","female:bikini","female:elf","female:glasses","female:halo","female:kemonomimi","female:nakadashi","female:ponytail","female:swimsuit","female:x-ray"],"thumb":"https://ehgt.org/w/02/204/91274-415j2sxe.webp","title":"[Jenoa Cake (Takayaki)] Abydos no Natsuyasumi (Blue Archive) [Digital]","title_jpn":"[じぇのばけーき (たかやKi)] アビドスの夏休み (ブルーアーカイブ) [DL版]","token":"ecf78522f4","torrentcount":"2","torrents":[{"added":"1758612396","fsize":"111257928","hash":"d0ed6d7a7480307055671d31f77d66f96ffede4e","name":"(C103) [じぇのばけーき (たかやKi)] アビドスの夏休み前編 (ブルーアーカイブ) [DL版].zip","tsize":"34378"},{"added":"1768576023","fsize":"97201889","hash":"458d91119a083381dce83f486ae9e3a3095dacbf","name":"(同人誌) [じぇのばけーき (たかやKi)] アビドスの夏休み (ブルーアーカイブ) [DL版].zip","tsize":"30096"}],"uploader":"raicoolloo"}