{"category":"Misc","dumped":1768568411,"expunged":false,"filecount":"302","filesize":872984879,"gid":3740663,"posted":"1768563585","rating":"2.08","tags":["female:kemonomimi","other:ai generated"],"thumb":"https://ehgt.org/w/02/204/63811-lf0hjqgk.webp","title":"私はあなた様のペットです 美々[AI Generated]","title_jpn":"","token":"702a07e79c","torrentcount":"1","torrents":[{"added":"1768563981","fsize":"855653555","hash":"29b929ed6a55255160030fcbd0c4e98cd8ef1c23","name":"私はあなた様のペットです 美々[AI Generated].zip","tsize":"65800"}],"uploader":"huiyuguxing"}