{"category":"Misc","dumped":1768554166,"expunged":false,"filecount":"167","filesize":79245423,"first_gid":"3157543","first_key":"a3bfa7082c","gid":3740425,"parent_gid":"3740392","parent_key":"5cf4016683","posted":"1768550981","rating":"2.24","tags":["language:english","male:big penis","male:muscle","female:big breasts","female:blowjob","female:cunnilingus","female:milf","other:compilation","other:full censorship","other:webtoon"],"thumb":"https://ehgt.org/w/01/677/69095-n9maswcf.webp","title":"Webtoon 69 position with DETAILED CHAPTERS","title_jpn":"","token":"306712ed65","torrentcount":"0","torrents":[],"uploader":"Girlxgirllover"}