{"category":"Image Set","dumped":1768625713,"expunged":false,"filecount":"9","filesize":22419204,"gid":3741745,"posted":"1768622292","rating":"0.50","tags":["parody:dig delight direct drive dj","female:big breasts","female:collar","female:nakadashi","female:paizuri","female:schoolgirl uniform","female:stockings","female:twintails"],"thumb":"https://ehgt.org/w/02/205/15075-pdurob7q.webp","title":"[VAL][244462] Esora-chan (Pixiv)","title_jpn":"[VAL][244462] 絵空ちゃん (Pixiv)","token":"1ecd663417","torrentcount":"1","torrents":[{"added":"1768622315","fsize":"22391880","hash":"1f54d2d33d557a653b65d07f8a5c0b60bf281e26","name":"[VAL][244462] Esora-chan (Pixiv).zip","tsize":"7160"}],"uploader":"AceNguyen"}