{"category":"Misc","dumped":1768627693,"expunged":false,"filecount":"117","filesize":77305749,"gid":3741825,"posted":"1768625433","rating":"1.63","tags":["parody:wuthering waves","character:lynae","male:first person perspective","female:big breasts","female:lactation","female:nakadashi","female:x-ray","other:ai generated","other:uncensored"],"thumb":"https://ehgt.org/w/02/178/51930-0m8utdle.webp","title":"鸣潮10 |琳奈 |KKKBBB [AI Generated]","title_jpn":"","token":"24ab47ffd9","torrentcount":"0","torrents":[],"uploader":"riiiiiiiiiiiiiiiii"}