{"category":"Misc","dumped":1768664813,"expunged":false,"filecount":"69","filesize":108402202,"gid":3742546,"posted":"1768662407","rating":"2.43","tags":["parody:honkai star rail","character:topaz","other:ai generated"],"thumb":"https://ehgt.org/w/02/106/78656-3tkvyte8.webp","title":"[G-apple] Topaz [AI Generated]","title_jpn":"","token":"720e13bd3f","torrentcount":"1","torrents":[{"added":"1768662539","fsize":"107423882","hash":"c9031466d2c030537c348b5df13ea589061ec923","name":"[G-apple] Topaz [AI Generated].zip","tsize":"16846"}],"uploader":"MoQiSzzKing"}