{"category":"Doujinshi","dumped":1768703644,"expunged":true,"filecount":"81","filesize":93076808,"gid":3743186,"posted":"1768696850","rating":"3.14","tags":["language:chinese","language:translated","group:broad smile","artist:sukage","male:shotacon","male:sole male","female:big breasts","female:daughter","female:harem","female:lolicon","female:mother","female:nakadashi","female:oyakodon","female:pregnant","female:sister","female:x-ray","mixed:group","mixed:incest","other:already uploaded","other:compilation","other:full color"],"thumb":"https://ehgt.org/w/01/158/90325-5m7d8kdr.webp","title":"[Broad smile (須影)] 家族姦えっち 1-3 [中国翻訳]","title_jpn":"[Broad smile (須影)] 家族姦えっち 1-3 [中国翻訳]","token":"7339b19c72","torrentcount":"0","torrents":[],"uploader":"CiaoP123"}