{"category":"Misc","dumped":1768831013,"expunged":false,"filecount":"1361","filesize":2131240704,"gid":3745815,"posted":"1768828150","rating":"1.00","tags":["female:lolicon","other:ai generated"],"thumb":"https://ehgt.org/w/02/209/04304-ksv3bmmg.webp","title":"ユティ pixiv [AI Generated]","title_jpn":"","token":"f552c39db5","torrentcount":"1","torrents":[{"added":"1768829596","fsize":"2123285155","hash":"664a7734163bce4c27ea59344d5625e7b3756ffd","name":"ユティ pixiv [AI Generated].zip","tsize":"81447"}],"uploader":"jjjie"}