{"category":"Western","dumped":1768805457,"expunged":false,"filecount":"21","filesize":18921789,"first_gid":"3568713","first_key":"3e0ad31343","gid":3745357,"parent_gid":"3732847","parent_key":"ad9ef64dc8","posted":"1768800501","rating":"4.65","tags":["language:english","artist:jjfrenchie","male:anal","male:anal intercourse","male:crossdressing","male:males only","male:stockings","male:tomgirl","male:yaoi","male:zombie","other:sketch lines"],"thumb":"https://ehgt.org/w/02/048/31645-dwgfeud4.webp","title":"[Joel Jurion] Raven","title_jpn":"","token":"5f09ffae66","torrentcount":"0","torrents":[],"uploader":"meficrow"}