{"category":"Misc","dumped":1768831013,"expunged":false,"filecount":"93","filesize":229820320,"gid":3745795,"posted":"1768827126","rating":"5.00","tags":["male:bald","other:ai generated"],"thumb":"https://ehgt.org/w/02/201/87948-5ui73jn3.webp","title":"[CEOofMommies] Tamaki Kousaka - To Heart 2 [Request] (Patreon) [AI Generated]","title_jpn":"","token":"ff863087c4","torrentcount":"1","torrents":[{"added":"1768827189","fsize":"229807342","hash":"28f6f6d61316b08126ea8d450e021810ab457c5f","name":"[CEOofMommies] Tamaki Kousaka - To Heart 2 [Request] (Patreon) [AI Generated].zip","tsize":"9147"}],"uploader":"ernie1234"}