{"category":"Misc","dumped":1768812512,"expunged":false,"filecount":"109","filesize":136816678,"first_gid":"3401794","first_key":"290ee8246e","gid":3745520,"parent_gid":"3401794","parent_key":"290ee8246e","posted":"1768808839","rating":"2.64","tags":["parody:chuunibyou demo koi ga shitai","character:rikka takanashi","male:big penis","female:lolicon","other:ai generated","other:mosaic censorship"],"thumb":"https://ehgt.org/w/01/890/55921-ccmy8aqo.webp","title":"小鸟游六花AI (yoyu) [AI Generated]","title_jpn":"","token":"b5be720230","torrentcount":"1","torrents":[{"added":"1768809207","fsize":"135190618","hash":"aa276f94c79fd722ed0a96730255aa630ce8b74b","name":"小鸟游六花AI (yoyu) [AI Generated].zip","tsize":"5489"}],"uploader":"jjjie"}