{"category":"Misc","dumped":1768845513,"expunged":false,"filecount":"135","filesize":434347106,"gid":3746228,"posted":"1768843655","rating":"4.44","tags":["other:ai generated"],"thumb":"https://ehgt.org/w/02/209/47056-ex5ap6op.webp","title":"[AiParadaise] Ariel [AI Generated]","title_jpn":"","token":"210aa3d94b","torrentcount":"1","torrents":[{"added":"1768843743","fsize":"434355340","hash":"7f8135de6ff6c1c6f70c2b69b736a63567636ce0","name":"[AiParadaise] Ariel [AI Generated].zip","tsize":"8625"}],"uploader":"KuruFapJikan"}