{"category":"Manga","dumped":1768973788,"expunged":false,"filecount":"214","filesize":110690262,"gid":3748518,"posted":"1768971225","rating":"1.61","tags":["language:chinese","language:translated","artist:nanao yukiji","other:already uploaded","other:compilation","other:rough translation","other:tankoubon"],"thumb":"https://ehgt.org/w/00/572/63953-n83m5b4l.webp","title":"[Nanao Yukiji] Niku Chichi DAYS（Chinese）","title_jpn":"[七尾ゆきじ] 肉乳DAYS","token":"cbb331466d","torrentcount":"0","torrents":[],"uploader":"lzmskyxz"}