{"category":"Doujinshi","dumped":1768985191,"expunged":false,"filecount":"8","filesize":3538961,"gid":3748700,"posted":"1768981780","rating":"4.17","tags":["language:chinese","language:translated","artist:kubikiri","female:guro","female:headless","female:necrophilia","female:rape","female:snuff"],"thumb":"https://ehgt.org/w/02/211/73801-qe1xzbhs.webp","title":"[Kubikiri] Kishi Winifureddo to Hime [Chinese][Dcliang個人漢化]","title_jpn":"[首切り] 騎士ウィニフレッドと姫 [中国翻訳]","token":"12fe535cad","torrentcount":"0","torrents":[],"uploader":"DCLⅰang"}