{"category":"Misc","dumped":1769011173,"expunged":false,"filecount":"80","filesize":107670895,"gid":3749284,"posted":"1769009164","rating":"1.20","tags":["male:dark skin","other:ai generated"],"thumb":"https://ehgt.org/w/02/212/28877-osm5fj0l.webp","title":"Rahmat Caesar BBC [AI Generated]","title_jpn":"","token":"47d2eaff3a","torrentcount":"1","torrents":[{"added":"1769009228","fsize":"107701033","hash":"5d5b3cd8666ff50deead93d169d8f4cdc1cbfb01","name":"Rahmat Caesar BBC [AI Generated].zip","tsize":"8542"}],"uploader":"Username5112007phat"}