{"category":"Western","dumped":1769071571,"expunged":false,"filecount":"55","filesize":24610098,"first_gid":"3634074","first_key":"56cb26e08c","gid":3750308,"parent_gid":"3746902","parent_key":"12b4560519","posted":"1769068916","rating":"4.63","tags":["language:english","artist:dirty bunny","male:furry","male:gokkun","male:masturbation","male:raccoon boy","male:sole male","female:furry","female:masturbation","female:milf","female:mother","female:nakadashi","female:raccoon girl","female:sex toys","female:sole female","mixed:incest","other:comic","other:full color"],"thumb":"https://ehgt.org/w/02/107/15582-txi6xgg1.webp","title":"[Dirty Bunny] Sound Connection (ongoing)","title_jpn":"","token":"6d2ac94277","torrentcount":"1","torrents":[{"added":"1767049019","fsize":"19113455","hash":"c7b996d25ec56eb30e9a4ebcec5b83c6db54fe2e","name":"[Dirty Bunny] Sound Connection (ongoing) [6BD6EB9C].zip","tsize":"12037"}],"uploader":"Masterbot"}