{"category":"Misc","dumped":1769094332,"expunged":false,"filecount":"115","filesize":62640754,"gid":3750727,"posted":"1769091534","rating":"1.00","tags":["parody:goddess of victory nikke","character:cinderella","male:big penis","male:dark skin","female:big breasts","female:blowjob","female:eye-covering bang","female:sole female","female:twintails","female:very long hair","other:ai generated"],"thumb":"https://ehgt.org/w/01/735/41958-av79yphn.webp","title":"Rahmat Cinderella BBC [AI Generated]","title_jpn":"","token":"48c2a1d310","torrentcount":"1","torrents":[{"added":"1769093461","fsize":"62087801","hash":"09dd8cc3f2bad8e545bb76d4b5ac0577a42e0b7c","name":"Rahmat Cinderella BBC [AI Generated].zip","tsize":"9805"}],"uploader":"Username5112007phat"}