{"category":"Misc","dumped":1769157628,"expunged":false,"filecount":"173","filesize":232616678,"gid":3751886,"posted":"1769153291","rating":"2.42","tags":["parody:senki zesshou symphogear","character:kirika akatsuki","other:ai generated","other:mosaic censorship"],"thumb":"https://ehgt.org/w/02/173/20044-azqrpa8s.webp","title":"KH Ai - Akatsuki Kirika 173p (Patreon) (AI Generated)","title_jpn":"","token":"bc7a940e4c","torrentcount":"1","torrents":[{"added":"1769153345","fsize":"232452152","hash":"1413cf5bff3753459ea898a249f811ba2788955d","name":"KH Ai - Akatsuki Kirika 173p (Patreon) (AI Generated).zip","tsize":"9223"}],"uploader":"xcyc"}