{"category":"Cosplay","dumped":1769191064,"expunged":false,"filecount":"17","filesize":38508256,"gid":3752648,"posted":"1769188142","rating":"1.71","tags":["parody:pokemon","character:umbreon","female:gloves","female:makeup","female:stockings","cosplayer:celebi","other:non-nude"],"thumb":"https://ehgt.org/w/02/104/39990-0bthhhtb.webp","title":"Celebi cosplay - Umbreon","title_jpn":"","token":"a30c85deec","torrentcount":"1","torrents":[{"added":"1769188234","fsize":"38462782","hash":"cf29b25408ba8b2c7eab24a1ef439d2cb9c22836","name":"Celebi cosplay - Umbreon.zip","tsize":"6193"}],"uploader":"b217285"}