{"category":"Misc","dumped":1769191064,"expunged":false,"filecount":"16","filesize":196566862,"gid":3752669,"posted":"1769188832","rating":"0.50","tags":["parody:nijisanji","character:inui toko","male:shotacon","male:smalldom","male:sole male","female:ahegao","female:big breasts","female:kemonomimi","female:sole female","female:vtuber","other:ai generated","other:mosaic censorship"],"thumb":"https://ehgt.org/w/02/215/32998-9tedbom5.webp","title":"[week2343] inui 買い出し [AI Generated]","title_jpn":"","token":"c4cc10f205","torrentcount":"0","torrents":[],"uploader":"Marishiten"}