{"category":"Misc","dumped":1769234121,"expunged":false,"filecount":"120","filesize":301806842,"gid":3753530,"posted":"1769231630","rating":"4.00","tags":["parody:neon genesis evangelion","character:asuka langley soryu","female:bukkake","female:schoolgirl uniform","female:sole female","female:twintails","mixed:group","other:ai generated"],"thumb":"https://ehgt.org/w/02/214/63412-a4kt8x8f.webp","title":"[Celistria] Asuka [AI Generated]","title_jpn":"","token":"85eb03bafb","torrentcount":"1","torrents":[{"added":"1769231702","fsize":"301870928","hash":"883d269ae0a7f76623f2c9c9c890d3a164801d5d","name":"[Celistria] Asuka [AI Generated].zip","tsize":"6083"}],"uploader":"卷着香奈美冲"}