{"category":"Doujinshi","dumped":1769228692,"expunged":false,"filecount":"15","filesize":36577986,"first_gid":"3736804","first_key":"9b9e203235","gid":3753455,"parent_gid":"3736804","parent_key":"9b9e203235","posted":"1769224763","rating":"2.85","tags":["language:chinese","language:translated","parody:genshin impact","parody:pokemon","parody:zenless zone zero","character:mable","character:nefer","artist:frozen spider lily","female:big breasts","female:nakadashi","female:sole female","female:stockings","other:uncensored"],"thumb":"https://ehgt.org/w/02/215/99303-e5vfei5a.webp","title":"[FrozenSpiderLily] 【短篇合集（小于10页）】| 最新更新日期：2026.1.23（中文）（q8Vxx译）","title_jpn":"","token":"70ba24e7e1","torrentcount":"0","torrents":[],"uploader":"q8Vxx"}