{"category":"Image Set","dumped":1769226343,"expunged":false,"filecount":"315","filesize":690471019,"first_gid":"3103270","first_key":"ea4941cf51","gid":3753354,"parent_gid":"3682523","parent_key":"9188f2f6ab","posted":"1769220195","rating":"4.56","tags":["parody:animal crossing","parody:blazblue","parody:digimon","parody:final fantasy vii","parody:pokemon","parody:shin megami tensei","parody:sonic the hedgehog","parody:super mario brothers","parody:the amazing digital circus","parody:tokyo afterschool summoners","character:azazel","character:buizel","character:cait sith","character:cusith","character:guilmon","character:impmon","character:incineroar","character:jax","character:jirachi","character:jubei","character:koops","character:krampus","character:miles tails prower","character:morgana","character:ophion","character:sakamoto","character:seth","character:squirtle","character:volos","character:yule","character:zangoose","character:zeraora","artist:tenpura","male:anal","male:anal intercourse","male:bbm","male:big penis","male:catboy","male:furry","male:yaoi"],"thumb":"https://ehgt.org/w/02/215/93075-7gopxlci.webp","title":"[Artist]Ra_Tenpu","title_jpn":"","token":"d4225a8597","torrentcount":"1","torrents":[{"added":"1736577969","fsize":"190223830","hash":"2ba2b4e11d8f45a80650bbd489a814a95cfdafa6","name":"[Artist]Ra_Tenpu.zip","tsize":"7566"}],"uploader":"CyBeRM00N"}