{"category":"Doujinshi","dumped":1769262991,"expunged":false,"filecount":"22","filesize":41733347,"gid":3754073,"posted":"1769260710","rating":"4.60","tags":["language:chinese","language:translated","parody:blue archive","character:alice tendou","character:sensei","group:inharmonicity","artist:hotokenoza","male:sole male","female:halo","female:nakadashi","female:sole female","female:very long hair"],"thumb":"https://ehgt.org/w/02/216/66927-9itmkoj4.webp","title":"[Inharmonicity (Hotokenoza)] My Dear ActL1s (Blue Archive) [Chinese] [欶澜汉化组] [Digital]","title_jpn":"[Inharmonicity (ホトケノザ)] My Dear ActL1s (ブルーアーカイブ) [中国翻訳] [DL版]","token":"0ee76bcede","torrentcount":"1","torrents":[{"added":"1769260784","fsize":"41451513","hash":"f89b85489a2c8cf32c2cd5ab4027dc49725bcf66","name":"[Inharmonicity (ホトケノザ)] My Dear ActL1s (ブルーアーカイブ) [中国翻訳] [DL版] [欶澜汉化组].zip","tsize":"3586"}],"uploader":"saibachu"}