{"category":"Doujinshi","dumped":1769326129,"expunged":false,"filecount":"43","filesize":91683660,"gid":3755497,"posted":"1769323791","rating":"2.75","tags":["language:spanish","language:translated","artist:fukuyama naoto","male:big penis","male:sole male","female:ahegao","female:big breasts","female:demon girl","female:fingering","female:kissing","female:multiple orgasms","female:twins","female:unusual pupils","mixed:ffm threesome","mixed:group"],"thumb":"https://ehgt.org/w/02/217/95528-5ydmu07k.webp","title":"SUCCUBUTIC 02 COMPILATION [SPANISH] [MANA]","title_jpn":"サキュバティック02コンピレーション","token":"19dc6a3f59","torrentcount":"1","torrents":[{"added":"1769323832","fsize":"85770103","hash":"12fabd85bba65617f4a548750464f1e1b0ff3728","name":"SUCCUBUTIC 02 COMPILATION [SPANISH] [MANA].zip","tsize":"34603"}],"uploader":"hatyan"}