{"category":"Misc","dumped":1769338270,"expunged":false,"filecount":"37","filesize":45818038,"gid":3755809,"posted":"1769335908","rating":"2.00","tags":["parody:blue archive","character:mutsuki asagi","female:halo","other:ai generated"],"thumb":"https://ehgt.org/w/02/218/23724-icrh519k.webp","title":"[Custom Firingu] Asagi Mutsuki (Blue Archive) [AI Generated]","title_jpn":"","token":"c07ab06f08","torrentcount":"1","torrents":[{"added":"1769335940","fsize":"45766204","hash":"b48f64b7c7b8ab3b9f91d1bc1698afde29094336","name":"[Custom Firingu] Asagi Mutsuki (Blue Archive) [AI Generated].zip","tsize":"7349"}],"uploader":"MoQiSzzKing"}