{"category":"Doujinshi","dumped":1769356758,"expunged":false,"filecount":"13","filesize":12985262,"gid":3756213,"posted":"1769354181","rating":"4.45","tags":["parody:pokemon","artist:mimonel","female:dark skin","other:full color"],"thumb":"https://ehgt.org/w/02/218/76525-av9nnwme.webp","title":"[Mimonel] Trainer-tachi no Ura Tournament | Trainers Secret Tournament (Pokémon LEGENDS Z-A)","title_jpn":"[ミモネル]トレーナーたちの裏トーナメント♥ (ポケモンレジェンズゼットエー)","token":"9aa8814ecc","torrentcount":"0","torrents":[],"uploader":"RedWoodOS"}