{"category":"Image Set","dumped":1769383749,"expunged":false,"filecount":"152","filesize":904134967,"first_gid":"3618688","first_key":"95d28f6247","gid":3756780,"parent_gid":"3713158","parent_key":"cab33eaac8","posted":"1769381277","rating":"4.35","tags":["parody:azur lane","parody:blue archive","female:big breasts","female:hairy","female:kemonomimi","female:lolicon","female:very long hair","other:uncensored"],"thumb":"https://ehgt.org/w/02/219/26807-gazkwbyb.webp","title":"[Fanbox] 柠檬鸡(-2026.1.26)","title_jpn":"","token":"4ebce9e634","torrentcount":"1","torrents":[{"added":"1767136281","fsize":"882547024","hash":"91221267624759d11d189de86c5e7f8f7a20b775","name":"[Fanbox] 柠檬鸡(-2025.12.6).zip","tsize":"34001"}],"uploader":"sh12357159"}