{"category":"Artist CG","dumped":1769351401,"expunged":false,"filecount":"5","filesize":6970537,"gid":3756021,"posted":"1769348065","rating":"3.88","tags":["artist:tina","male:sole male","female:beauty mark","female:garter belt","female:sole female","female:stockings","other:mosaic censorship","other:variant set"],"thumb":"https://ehgt.org/w/02/218/59690-2k827540.webp","title":"[Tina] 泣きぼくろのポニテ爆乳お姉さん","title_jpn":"[Tina] 泣きぼくろのポニテ爆乳お姉さん","token":"f733f489cd","torrentcount":"0","torrents":[],"uploader":"ninetydollardoujin"}