{"category":"Misc","dumped":1769412983,"expunged":false,"filecount":"270","filesize":125431642,"first_gid":"3753210","first_key":"f457ee167b","gid":3757231,"parent_gid":"3753210","parent_key":"f457ee167b","posted":"1769409745","rating":"1.75","tags":["other:ai generated"],"thumb":"https://ehgt.org/w/02/215/82884-qkjvniud.webp","title":"[Pixiv] (ユキ) (31780358) 2 [AI Generated]","title_jpn":"","token":"b774a214d9","torrentcount":"1","torrents":[{"added":"1769409823","fsize":"121988300","hash":"137a17d0d9b8498bcfc63c5e10289306f36316b8","name":"[Pixiv] (ユキ) (31780358) 2 [AI Generated].zip","tsize":"9654"}],"uploader":"asesino55544"}