{"category":"Western","dumped":1769426952,"expunged":false,"filecount":"29","filesize":58061171,"first_gid":"3504739","first_key":"4b5385493c","gid":3757412,"parent_gid":"3752248","parent_key":"a34f1dc986","posted":"1769423327","rating":"2.94","tags":["language:english","language:translated","parody:the simpsons","character:marge simpson","artist:drah navlag","male:bald","male:glasses","male:midget","male:old man","male:unusual pupils","female:big ass","female:big breasts","female:collar","female:lingerie","female:milf","other:comic","other:full color"],"thumb":"https://ehgt.org/w/01/987/51315-asub6dau.webp","title":"The Yellow Fantasy 18 - Hans Moleman Show (The Simpsons) [English]","title_jpn":"","token":"dc42d7b65d","torrentcount":"0","torrents":[],"uploader":"monkey132"}