{"category":"Misc","dumped":1769503710,"expunged":false,"filecount":"36","filesize":49080745,"gid":3758828,"posted":"1769500306","rating":"0.50","tags":["other:ai generated"],"thumb":"https://ehgt.org/w/02/221/39631-np12thu7.webp","title":"Igawa Sakura / 井河さくら [AI Generated]","title_jpn":"sasuga_yukke","token":"2c8697b671","torrentcount":"1","torrents":[{"added":"1769500359","fsize":"48699128","hash":"8617085b663626712c72fb5da389af73610c2111","name":"Igawa Sakura  井河さくら [AI Generated].zip","tsize":"7773"}],"uploader":"koregarequiemdaa32"}