{"category":"Doujinshi","dumped":1769468406,"expunged":false,"filecount":"18","filesize":44162360,"gid":3758243,"posted":"1769466041","rating":"4.00","tags":["language:portuguese","language:rewrite","artist:kizaru","male:shotacon","female:big breasts"],"thumb":"https://ehgt.org/w/02/219/27896-o9oa4t35.webp","title":"[Kizaru] Mamakan Club Extra Chapter [Portuguese-BR]","title_jpn":"","token":"0e4fec7137","torrentcount":"1","torrents":[{"added":"1769466184","fsize":"44034672","hash":"4913fc8d9aa6b5c7d17877f86f600e65e6d37e1c","name":"[Kizaru] Mamakan Club Extra Chapter [Portuguese-BR].zip","tsize":"18032"}],"uploader":"nier404"}