{"category":"Western","dumped":1769532064,"expunged":false,"filecount":"10","filesize":35382894,"first_gid":"3734216","first_key":"6cc10649a5","gid":3759511,"parent_gid":"3734216","parent_key":"6cc10649a5","posted":"1769529224","rating":"2.58","tags":["language:english","parody:deltarune","character:queen","character:ralsei","character:susie","artist:eviltqf","male:absorption","male:furry","male:sheep boy","male:snuff","male:vore","female:absorption","female:big ass","female:big breasts","female:big nipples","female:femdom","female:furry","female:huge breasts","female:lizard girl","female:robot","female:snuff","female:vore","other:comic","other:full color"],"thumb":"https://ehgt.org/w/02/222/08174-u7lde9mm.webp","title":"[EvilTQF] The Treatment you Deserve","title_jpn":"","token":"55a787ecab","torrentcount":"0","torrents":[],"uploader":"masterreviewer1000"}