{"category":"Image Set","dumped":1769522438,"expunged":false,"filecount":"1021","filesize":1427886963,"first_gid":"2695177","first_key":"d2c436f705","gid":3759200,"parent_gid":"3756088","parent_key":"4283d96e15","posted":"1769519075","rating":"4.74","tags":["parody:vocaloid","character:miku hatsune","artist:abmayo","female:anal","female:anal intercourse","female:big breasts","female:bikini","female:blindfold","female:bondage","female:detached sleeves","female:furry","female:gag","female:handjob","female:kemonomimi","female:leotard","female:masturbation","female:nakadashi","female:painted nails","female:pantyhose","female:pasties","female:sex toys","female:shimapan","female:small breasts","female:stockings","female:swimsuit","female:tentacles","female:twintails","female:urination","female:very long hair","other:mosaic censorship"],"thumb":"https://ehgt.org/w/02/218/65283-8n2jd057.webp","title":"[Pixiv] abmayo (17332140)","title_jpn":"","token":"1e5ec4081b","torrentcount":"25","torrents":[{"added":"1696412978","fsize":"766402059","hash":"5fd78a44a01c5ae3f020eb8e48844f7d86dd25c0","name":"[2023-10-03 14 20][Pixiv] abmayo (17332140).zip","tsize":"29611"},{"added":"1709132246","fsize":"822076065","hash":"507fb3bacfb372a3a684d6728c2af52e4acbf977","name":"[Pixiv] abmayo (17332140) [2024-02-28].zip","tsize":"31732"},{"added":"1717948333","fsize":"718413844","hash":"741cb47ed2d8dd77864ed7a07b5fb82cfd1aa9ab","name":"2934290_f43889cecf.7z","tsize":"27728"},{"added":"1730522232","fsize":"971302962","hash":"5491e4cad2a064c0ac37235197701bded464e193","name":"[Pixiv] abmayo (17332140) [2024-10-31].zip.zip","tsize":"37393"},{"added":"1737989810","fsize":"1006042148","hash":"57417cabc1acb8f5a39731795d8d3be88ffcf54f","name":"[Pixiv] abmayo (17332140) [2025-01-25].zip","tsize":"100327"},{"added":"1738799295","fsize":"1007617568","hash":"9c54be7c5d132d3a3f53ad4727bde8cf57d6de5a","name":"[Pixiv] abmayo (17332140) [2025-01-25].zip","tsize":"100483"},{"added":"1740608880","fsize":"1009799064","hash":"20c11688fd1c03438472329e069b1f28200eb443","name":"[Pixiv] abmayo (17332140) [2025-02-17].zip","tsize":"100743"},{"added":"1741390572","fsize":"1012090110","hash":"e85f64485afa4b2e874720c691013aed40ef81f1","name":"[Pixiv] abmayo (17332140).zip","tsize":"38954"},{"added":"1741788828","fsize":"1012777534","hash":"3f0c5937fdbb1af1269e2347333ad7582cacf729","name":"[Pixiv] abmayo (17332140) [2025-03-07].zip","tsize":"101003"},{"added":"1743200746","fsize":"1019241936","hash":"3ea8248c159eec5f4bd3ff352705a7a9be49e4f6","name":"[Pixiv] abmayo (17332140) [2025-03-16].zip","tsize":"101679"},{"added":"1744305232","fsize":"1042219428","hash":"be1e75aa1e5dfa9ea6b80d731acc109f2d085d73","name":"[Pixiv] abmayo (17332140).zip","tsize":"40094"},{"added":"1744998937","fsize":"1042896807","hash":"66a93405a7f035bc34e1f7ed378de68b688397bf","name":"[Pixiv] abmayo (17332140) [2025-04-10].zip","tsize":"40130"},{"added":"1748030830","fsize":"1089264230","hash":"80ddd058650b41863d0b068f61c01df107b48c94","name":"[Pixiv] abmayo (17332140) [2025-05-23].zip","tsize":"41890"},{"added":"1749158372","fsize":"1105155670","hash":"913dc1139cd0f98ba5be48dbe4eccd8b73731152","name":"[Pixiv] abmayo (17332140) [2025-06-05].zip","tsize":"42490"},{"added":"1750920445","fsize":"1110370152","hash":"eb9eb574c0bc74bbb0e8eff25914c3b568bb8f48","name":"[Pixiv] abmayo (17332140).zip","tsize":"10935"},{"added":"1751729595","fsize":"1122979712","hash":"a341f175b72d8528148ddbbc28c4143dc6db7a73","name":"[Pixiv] abmayo (17332140) [2025-07-05].zip","tsize":"43170"},{"added":"1753903428","fsize":"1148174103","hash":"889d11baab5422d75e0400693b75d9efce72dc94","name":"[Pixiv] abmayo (17332140) [2025-07-28].zip","tsize":"44130"},{"added":"1755746727","fsize":"1180242289","hash":"4646066b1670d973e2fc0d2889ed7fa632ff7c4b","name":"[Pixiv] abmayo (17332140) [2025-08-18].zip","tsize":"45370"},{"added":"1759286270","fsize":"1223399946","hash":"620bc86effab4bed90c7074f2fd8646290753c3e","name":"[abmayo] (17332140) (2025-09-30).zip","tsize":"121895"},{"added":"1759675908","fsize":"1243573622","hash":"1a86bdcaac724bf7caa04db784d7446db79a9550","name":"[Pixiv] abmayo (17332140) [2025-10-05].zip","tsize":"47770"},{"added":"1760928725","fsize":"1268617203","hash":"448bfab53a70a0475e0cbd14b813bb9f9dbaaaa1","name":"[Pixiv] abmayo (17332140) [2025-10-17].zip","tsize":"48730"},{"added":"1762739871","fsize":"1294289574","hash":"649086f6f75db2d0d5e51bcd977695410ac6d280","name":"[Pixiv] abmayo (17332140) [2025-11-07].zip","tsize":"49710"},{"added":"1764870712","fsize":"1331518795","hash":"424b8b297c7c59b416824b480cfe0fb277bfed88","name":"[Pixiv] abmayo (17332140) [3669019].zip","tsize":"132625"},{"added":"1766515723","fsize":"1366111095","hash":"278a9eb35f097a36d1911af3ed86b8398721d997","name":"[Pixiv] abmayo (17332140) [2025-12-23].zip","tsize":"52450"},{"added":"1767780139","fsize":"1378144304","hash":"1d27c05afc53c36c76ce9270e7e917513570e825","name":"[Pixiv] abmayo (17332140) - 1015 pages.zip","tsize":"26631"}],"uploader":"114514beastman"}