{"category":"Misc","dumped":1769525039,"expunged":false,"filecount":"28","filesize":40173462,"gid":3759292,"posted":"1769522164","rating":"1.75","tags":["language:speechless","other:ai generated"],"thumb":"https://ehgt.org/w/02/221/65368-mjzof0rd.webp","title":"[Isterya] Yae Miko Onsen (textless) [AI Generated]","title_jpn":"","token":"3798f50450","torrentcount":"1","torrents":[{"added":"1769523955","fsize":"40132789","hash":"b41d95c21009d5f310ffc94c65d5d407217ca7d7","name":"[Isterya] Yae Miko Onsen (textless) [AI Generated].zip","tsize":"6479"}],"uploader":"KuruFapJikan"}