{"category":"Misc","dumped":1769608814,"expunged":false,"filecount":"105","filesize":158616572,"gid":3760685,"posted":"1769604540","rating":"4.50","tags":["parody:pokemon","character:dawn","female:sleeping","other:ai generated","other:uncensored"],"thumb":"https://ehgt.org/w/02/223/40252-g7z87xpg.webp","title":"[Hanousen_2] Dawn (Pokémon) [AI Generated] [Uncensored]","title_jpn":"","token":"545590a5b5","torrentcount":"1","torrents":[{"added":"1769604668","fsize":"158656155","hash":"fc00a192b5207f24362d27f529218497210baaf1","name":"[Hanousen_2] Dawn (Pokémon) [AI Generated] [Uncensored].zip","tsize":"12618"}],"uploader":"hirofuru"}