{"category":"Misc","dumped":1769619363,"expunged":false,"filecount":"1348","filesize":2838297979,"first_gid":"3484482","first_key":"f167bdbe7f","gid":3761020,"parent_gid":"3674228","parent_key":"7f762bd36e","posted":"1769614589","rating":"1.91","tags":["language:chinese","parody:genshin impact","parody:honkai gakuen","parody:honkai star rail","parody:koikatsu","parody:princess connect","parody:yu-gi-oh","character:aether","character:caelus","character:firefly","character:keqing","character:kiana kaslana","character:pecorine","character:pelageya sergeyevna","character:raiden shogun","character:sky striker ace - raye","character:sparkle","character:theresa apocalypse","male:dark skin","male:muscle","female:big breasts","female:corruption","female:netorare","female:pantyhose","female:yuri","other:3d","other:3d imageset"],"thumb":"https://ehgt.org/w/01/951/14291-pzmwim40.webp","title":"[Pixiv] 可以瑟瑟 (4) (6970604)","title_jpn":"","token":"214682925e","torrentcount":"0","torrents":[],"uploader":"Human. People"}