{"a":"Mant","c":["l:english","l:translated","a:gura","m:insect","f:bestiality","f:body modification","f:bondage","f:impregnation","f:insect","f:nakadashi","f:pregnant","f:rape","f:small breasts","f:tentacles","f:vaginal birth","f:witch","f:x-ray","o:multi-work series"],"d":"I saw that the beacons got lit, so here's the TL for chapter three.<br><br>This one had a fair bit of dialogues going on, so I went for a more readable font than my previous uploads.<br>Likewise I translated the sfx at my own discretion trying to balance understanding the non-verbal action while also trying not to alter the original image too much.<br><br>Gotta love those umbilical cords at the end, 100% blood related pregnancy.<br><br>Have fun, ducklings.","g":3731856,"i":"https://ehgt.org/w/02/168/47097-irl0hj4d.webp","n":"[Doujinshi] [Gura Craft] Onna Mahoutsukai-san Mushikan Hanashi 3 [English] {Mant}","p":1768078944,"t":"be55453f57"}