{"a":"alfredmeow","c":["l:english","l:translated","a:kira hiroyoshi","m:muscle","m:sole male","m:sweating","f:big breasts","f:cunnilingus","f:glasses","f:hair buns","f:handjob","f:hidden sex","f:lab coat","f:nakadashi","f:sole female","f:sweating","o:full color","o:multi-work series","o:story arc","o:uncensored","lo:bathing room"],"g":3733924,"i":"https://ehgt.org/w/02/168/58211-1ub36oo8.webp","n":"[Manga] [Kira Hiroyoshi] Dekichau made Kon ~Bijo Doctor to Zuppuri Haramase Seikatsu | Marry Me, Ill Fuck You Until You're Pregnant! Vol. 1-3 [English] [Decensored] [Ongoing]","p":1768179044,"t":"8bc59919a3"}