{"a":"Mornth","c":["l:english","p:x-men","c:emma frost","c:jean grey","a:mornth","f:bdsm","f:bondage","f:gag","f:gloves","f:yuri","o:comic","o:full color"],"d":"Hey everyone,<br><br>Here, you'll find the official release of my comic : Frostbound Academy - The Rivalry (first issue).<br><br>I'll publish 3 page every month in early access on my Substar ⭐: <br><br>- https://subscribestar.adult/mornth<br><br>Don't hesitate to comment or give feedback and in any case, I hope you enjoy the comic 😉","g":3733692,"i":"https://ehgt.org/w/02/066/66993-6hua1hd7.webp","n":"[Western] [Mornth] Frostbound Academy - The Rivalry 001 (Ongoing)","p":1768168375,"t":"97efb1fcf9"}