{"a":"BigWillyHaver69","c":["p:blue archive","a:houkou sakuran","f:big breasts","houkou"],"d":"Support: https://www.pixiv.net/fanbox/creator/2671042<br>Cost: Not that much.<br><br>Reviving this gallery since the creator is nuking their previous content at the end of this month (9/29/25), and is going on a per-monthly release basis.<br><br>Always remember, folks, it pays to archive.","g":3736989,"i":"https://ehgt.org/w/01/147/16652-i6epkul9.webp","n":"[Image Set] [Fanbox] 方向錯亂 / Houkou","p":1768358963,"t":"95de4aa3fe"}