{"a":"samuraidemonslayer","c":["l:english","p:winx club","a:inuyuru","f:tentacles"],"d":"A Winx Club comic made by Inuyuru, commissioned by someone who wants to remain anonymous<br><br>Disclaimer: The anonymous commissioner and writer of this comic, the artist of this comic, or I, the uploader of this comic, do not own Winx Club<br><br>Please help support Inuyuru<br>https://twitter.com/inuyurusamakun?lang=en<br>https://www.patreon.com/Inuyuru<br><br>Although the writer wants to remain anonymous, they appreciate any monetary donation to help them financially<br>To find their ko-fi account go to this link<br>https://www.deviantart.com/samuraidemonslayer9/journal/Anonymous-comic-writer-877860647","g":3738709,"i":"https://ehgt.org/w/01/209/61178-3drx09qn.webp","n":"[Western] [Inuyuru] Potion Mishap: Bloom (Winx Club) [Incomplete]","p":1768455410,"t":"0a1c4ecc19"}