{"a":"Rogabute","c":["l:speechless","p:pokemon","c:ansha","c:glaceon","c:hoopa confined","c:sylveon","a:dagasi","m:bisexual","m:furry","m:human on furry","m:yaoi","f:anal","f:anal intercourse","f:double penetration","f:lolicon","f:nakadashi","f:sole female","mi:group","mi:mmf threesome","o:uncensored"],"d":"https://baraag.net/@DAGASI/115888384181121417<br>https://baraag.net/@DAGASI/115899708833732868<br><br>Censored Gallery (Complete):<br>https://e-hentai.org/g/3731872/f49f5a7711/","g":3739994,"i":"https://ehgt.org/w/02/201/08946-a0huh99b.webp","n":"[Artist CG] [DAGASI] Dareka ga Yume Mite Shimatta Hatsujou Pokemon Shika Inai Ijigen Miare ni Mayoikomu (Pokémon LEGENDS Z-A) [Decensored]","p":1768523505,"t":"146bb56546"}