{"a":"kikimaru024","c":["p:darkstalkers","p:kono subarashii sekai ni syukufuku o","c:lilith aensland","c:megumin","a:neocoill","m:big penis","m:multiple orgasms","m:sole male","f:anal","f:anal intercourse","f:big ass","f:big breasts","f:blowjob","f:cosplaying","f:leotard","f:nakadashi","f:paizuri","f:pantyhose","f:sole female","f:wings","o:western cg"],"d":"https://www.patreon.com/NeoCoill<br>https://bsky.app/profile/neocoill.bsky.social<br>https://linktr.ee/NeoCoill<br>https://twitter.com/NeoCoillHQ","g":3739142,"i":"https://ehgt.org/w/02/203/16556-9urjfr3o.webp","n":"[Western] [NeoCoill] Subarashii Succubi (KonoSuba)","p":1768482099,"t":"7e0ca16f11"}