{"a":"zerpientez","c":["l:english","a:bernin","m:asphyxiation","m:bdsm","m:cbt","m:chastity belt","m:clothed female nude male","m:collar","m:guro","m:large insertions","m:leash","m:nipple stimulation","m:onahole","m:ryona","m:shotacon","m:slave","m:torture","m:trampling","f:big breasts","f:femdom","f:footjob","f:lolicon","f:maid","f:nakadashi","f:netorare","f:pantyhose","f:schoolgirl uniform","f:smell","f:stockings","f:thigh high boots","o:no penetration"],"d":"Works from bernin's fanbox, that were not on the site, in chronological order, mainly from the dates mentioned in the title except for the first 2 images which are from january 16 2024.<br><br>24/08/2025 Added 2 new sets at the end of the gallery<br>15/01/2026 Added 3 new sets at the end of the gallery<br>16/01/2026 Added 2 new sets at the end of the gallery<br><br>https://bernin.fanbox.cc/<br>https://fantia.jp/fanclubs/504326<br>https://www.pixiv.net/users/12232566","g":3740028,"i":"https://ehgt.org/w/01/948/64776-2pkwp9h5.webp","n":"[Image Set] [Bernin] Femdom/Feet/CBT Fanbox April 14/2025 - October 25/2025 (500 Yen Plan) [English]","p":1768526400,"t":"b9b26d4468"}