{"a":"114514beastman","c":["p:blue archive","p:metroid","p:zenless zone zero","c:miku hatsune","c:samus aran","c:zhu yuan","a:xipa","m:big balls","m:big penis","m:dark skin","m:feminization","m:horse cock","m:monster","f:all the way through","f:anal","f:ball sucking","f:big areolae","f:big ass","f:big balls","f:big breasts","f:big penis","f:bikini","f:blowjob","f:bodysuit","f:business suit","f:centaur","f:corruption","f:dark skin","f:deer girl","f:demon girl","f:dickgirl on female","f:eye-covering bang","f:full-packaged futanari","f:futanari","f:futanarization","f:gaping","f:glasses","f:halo","f:high heels","f:horns","f:horse cock","f:hotpants","f:huge breasts","f:huge penis","f:kemonomimi","f:maid","f:milf","f:muscle","f:nun","f:onahole","f:paizuri","f:parasite","f:policewoman","f:ponytail","f:randoseru","f:rape","f:schoolgirl uniform","f:shemale","f:stockings","f:tail","f:tentacles","f:transformation","f:twintails","f:urethra insertion","f:very long hair","f:wings","f:x-ray"],"d":"https://www.pixiv.net/users/75450767<br>https://xipa.fanbox.cc/posts/8323468<br>https://fantia.jp/fanclubs/503222<br>https://www.patreon.com/Xipa645","g":3744228,"i":"https://ehgt.org/w/02/207/83692-5zj3ppfa.webp","n":"[Image Set] [Pixiv] Xipa (75450767)","p":1768751123,"t":"6e449be258"}