{"a":"westfall","c":["l:korean","l:translated","p:pokemon","g:chimple hotters","a:chimple hotter","f:big breasts","f:dark skin","f:maid"],"d":"RAW: https://e-hentai.org/g/3744644/746679b343/<br><br>공준이는 장식일 뿐 메인은 시온을 조교하는 유카리<br><br>솔직히 카나리 무쿠보다 이 둘이 더 꼴림 ㅇㅇ","g":3748815,"i":"https://ehgt.org/w/02/211/73790-4okazwi9.webp","n":"[Doujinshi] (C107) [Chimple Hotters (Chimple Hotter)] Sex Shinai to Derarenai Yukari Zone | 섹스하지 않으면 나갈 수 없는 유카리 존 (Pokémon LEGENDS Z-A) [Korean]","p":1768986479,"t":"454650abb2"}