{"a":"ioctl","c":["p:touhou project","c:junko","c:mamizou futatsuiwa","c:ran yakumo","c:reisen udongein inaba","c:yukari yakumo","g:azukigayu","a:azuki osamitu"],"d":"https://www.melonbooks.co.jp/detail/detail.php?product_id=246848<br>https://forums.e-hentai.org/index.php?showtopic=292035<br><br>Thanks to cholaster for his scan/rip service.<br><br>If anyone with a real seeding setup wants to make a torrent with the \"original\" pdfs, PM me for the file on the forums, because I don't have one.","g":3757268,"i":"https://ehgt.org/w/02/219/56477-a83ie7il.webp","n":"[Non-H] [Azukigayu (Azuki Osamitu)] Gensou Retro Shopping (Touhou Project) [Digital]","p":1769412556,"t":"3e5c20fd23"}