{"a":"NeetFreak56","c":["l:text cleaned","p:azur lane","p:blue archive","p:dragon ball","p:fate grand order","p:genshin impact","p:honkai star rail","p:kono subarashii sekai ni syukufuku o","p:league of legends","p:my hero academia","p:naruto","p:pokemon","p:saki","p:the idolmaster","p:touhou project","p:zenless zone zero","c:android 19","c:aqua","c:arlecchino","c:asuna ichinose","c:chizuru ichinose","c:chun-li","c:cynthia","c:evelyn","c:fuyuko mayuzumi","c:hinata hyuga","c:kafka","c:makima","c:marin kitagawa","c:mei raiden","c:nodoka haramura","c:shouko komi","c:temari","c:topaz","c:tsunade","c:yor forger","c:yun yun","c:yunyun","o:themeless"],"d":"+1207 pics 22-Dec-2025<br>+65 pics 25-Dec-2025","g":3759525,"i":"https://ehgt.org/w/02/160/38500-op6i4o9a.webp","n":"[Misc] Random clear .png Images(sfw & nsfw)","p":1769529619,"t":"abd025a791"}