{"a":"Johnjacobsjamesonthe","c":["l:english","p:dinosaur king","p:dragon ball gt","p:droners","p:dungeons and dragons","p:fushigi no umi no nadia","p:lilo and stitch","p:looney tunes","p:pokemon","p:sailor moon","p:teen titans","p:the boondocks","p:the jungle book","p:the little mermaid","p:thundercats","p:totally spies","c:ariel","c:bumblebee","c:cheetara","c:chi chi","c:diana the acrobat","c:jazmine dubois","c:misty","c:mowgli","c:nadia la arwall","c:pan","c:panda delgado","c:sailor jupiter","c:sailor mars","c:sailor mercury","c:sailor moon","c:sailor venus","c:starfire","c:wile e. coyote","c:zoe drake","a:arabatos","m:dark skin","m:exhibitionism","m:facesitting","m:furry","m:necrophilia","m:ryona","m:shotacon","m:smalldom","m:sole male","f:anal","f:asphyxiation","f:bald","f:big ass","f:big breasts","f:blowjob","f:dark skin","f:exhibitionism","f:futanari","f:guro","f:lolicon","f:milf","f:necrophilia","f:rape","f:ryona","f:shemale","f:snuff","f:tanlines","f:underwater sex","f:very long hair","o:comic","o:full color"],"d":"Please be a part of the conversation at<br><br>https://forums.e-hentai.org/index.php?showtopic=239786<br><br>https://discord.gg/yDAHS6K<br><br>Also if you want to help contribute monetary just hop on the discord <br><br>Rules:<br>1: All contestants in the Death Games will fight completely in the nude or at least wear very skimpy clothing.<br>2: Battles will be either male-vs.-female, female-vs-female, or both simultaneously.<br>3: Most fighting will be done unarmed, although certain weapons such as pillows, plastic bags, garrottes, etc. shall be permitted.<br>4: All deaths must be inflicted via asphyxiation, i.e. strangulation, drowning, or smothering. Any other form of death is prohibited, although accidental deaths such as those from falls are considered incidental, and will not be penalized.<br>5: All contestants, both male and female, must be between the ages of 10 to 55 and be reasonably attractive members of humanoid species.<br>6: Participants who are disqualified will be subject to a penalty death by asphyxiation.<br>7: Participants are strongly encouraged to sexually assault their opponents before or during the process of killing them. Doing so will award bonus cash to the survivor. Post-mortem rapes will earn no bonus, but are not punishable offenses.<br><br>Edit Imagine Misty said \"Sweet Arceus\"","g":3761392,"i":"https://ehgt.org/w/00/816/59880-36vngb7r.webp","n":"[Western] [Arabatos] Death Games 3 Remake (Various) [Ongoing]","p":1769632592,"t":"3f073d8581"}